<DAY>
<SAINT Name="2" Cmd="dow == 0" />
<SAINT Name="8" Cmd="dow == 6" />

<SAINT Name="St Boniface et Aglaïs la Romaine" Id="437" Type="1" />
<SAINT Name="Sts Elie, Probos et Arès" Id="3147" Type="0" />
<SAINT Name="Sts Timothée et Polyeucte" Id="" Type="0" />
<SAINT Name="Sts Eutychès, Thessalonique et leurs 270 compagnons" Id="" Type="0" />
<SAINT Name="St Tryphon" Id="" Type="0" />
<SAINT Name="St Grégentios, Evêque de Safar" Id="" Type="0" />
<SAINT Name="St Elie de Mourom" Id="942" Type="0" />

</DAY>