<DAY><SAINT SId="257512" CId="257512"/>
<SAINT SId="6969" CId="6969"/>
<SAINT SId="36902" CId="36902"/>
<SAINT SId="11250097" CId="11250097"/>
<SAINT SId="11250197" CId="11250197"/>
<SAINT SId="112403" CId="112403"/>
<SAINT SId="11250397" CId="11250397"/>
<SAINT SId="11250497" CId="11250497"/>
<SAINT SId="11250597" CId="11250597"/>
<SAINT SId="11240199" CId="11240199"/>
<SAINT SId="11250797" CId="11250797"/>
<SAINT SId="11250897" CId="11250897"/>
<SAINT SId="11250997" CId="11250997"/>
<SAINT SId="11251097" CId="11251097"/>
<SAINT SId="152101" CId="152101"/>
<SAINT SId="2017" CId="2017"/>
<SAINT SId="11240100" CId="11240100"/>
<SAINT SId="112407" CId="112407"/>
<SAINT SId="112411" CId="112411"/>
</DAY>
