<SAINT>
<LANGUAGE Cmd="LS == 3">
<NAME Nominative="Иконы Божией Матери, именуемой Троеручица"/> 
<LIFE Id="bulgakov" Copyright="Настольная книга свщеннослужителя. Москва. 1978.">
Чудотворный образ, пред которым получил исцеление отрубленной руки препо- добный Иоанн Дамаскин (память 4 декабря), передан им в Лавру преподобного Саввы Освященного. В XIII веке святая икона находилась в Сербии, а впоследствии чудесно перенесена на Афон в Хилендарский монастырь. Более подробные сведения об иконе помещены 28 июня. 
</LIFE>
<TROPARION Tone="1">

</TROPARION>
<KONTAKION Tone="1">

</KONTAKION>

</LANGUAGE>
<LANGUAGE Cmd="LS == 0">
<NAME Nominative="Icon of the Mother of God, named &quot;Three-Handed&quot;"/> 
<LIFE Id="bulgakov" Copyright="The Clergyman's Handbook. Moscow. 1978. English translation Copyright 1997 Fr. S. Janos.">
The wonderworking image, before which the Monk John Damascene (Comm. 4 December) received healing of a cut-off hand, was given over by him to the Laura of the Monk Sava the Sanctified. In the XIII Century the icon was situated in Serbia, and afterwards it was miraculously transported to Athos to the Khilendaria monastery. A more detailed account about the icon is located under 28 June. 
</LIFE>
<TROPARION Tone="1">

</TROPARION>
<KONTAKION Tone="1">

</KONTAKION>
</LANGUAGE>
</SAINT>