<DAY>

<SAINT Name="聖彌特若梵（君士坦丁堡首位榮膺牧首銜之主教，325年）" Id="1224" Type="1" />
<SAINT Name="聖女瑪利亞及聖女瑪爾塔（聖拉匝若之姊妹，一世紀）" Id="" Type="0" />
<SAINT Name="殉道者弗榮塔西，塞維里諾，塞維里安，西拉諾（高盧，一世紀）" Id="" Type="0" />
<SAINT Name="殉道司教阿斯提（馬其頓的迪拉希翁城主教，110年）" Id="" Type="0" />
<SAINT Name="殉道者孔科爾迪（斯頗萊托，175年）" Id="" Type="0" />
<SAINT Name="聖提托（拜占庭城主教，三世紀）" Id="" Type="0" />
<SAINT Name="殉道司祭阿頗塔基、殉道者：喀瑪若、佐提科、伽達諾、寧尼托、猶利、阿塔洛、艾弗提希、阿瑪索、喀里諾、薩圖爾尼諾、及其餘三十位殉道者（以上諸位殉道者均在小錫西厄的諾維奧頓翁城被斬首，320年）" Id="" Type="0" />
<SAINT Name="聖奧普塔托（努米底亞的米樂文城主教，376年）" Id="" Type="0" />
<SAINT Name="聖阿洛尼（埃及的斯凱特地方，五世紀）" Id="" Type="0" />
<SAINT Name="殉道者佐提科、阿塔洛、喀瑪西、斐利普（羅馬尼亞，四世紀）" Id="" Type="0" />
<SAINT Name="聖佐西瑪（西里西亞人氏，埃及的新巴比倫城主教，六世紀）" Id="" Type="0" />
<SAINT Name="殉道修士約安（基茲科附近之摩納哥里亞修道院院長，761年）" Id="" Type="0" />
<SAINT Name="聖女索斐亞（色雷斯，十至十一世紀）" Id="" Type="0" />
<SAINT Name="聖麥托迪（拉多奈哲的聖塞爾吉之弟子，佩示諾沙修道院院長，1392年）" Id="" Type="0" />
<SAINT Name="聖埃勒阿匝爾及聖納匝里（奧洛奈茨之顯行靈蹟者，十五世紀）" Id="" Type="0" />
<SAINT Name="殉道司教約阿尼科（塞爾維亞的黑山和濱海區都主教，1941年）" Id="" Type="0" />
<SAINT Name="殉道司教薩瓦（上卡爾洛維茨主教，1941年）" Id="" Type="0" />
<SAINT Name="聖裴特若克（康沃爾，594年）" Id="" Type="0" />

</DAY>