<DAY>
<SAINT SId="110801" CId="110801"/>
<SAINT SId="05201100" CId="05201100"/>
<SAINT SId="052001" CId="052001"/>
<SAINT SId="052000" CId="052000"/>
<SAINT SId="05200595" CId="05200595"/>
<SAINT SId="110901" CId="110901"/>
<SAINT SId="05200395" CId="05200395"/>
<SAINT SId="05201200" CId="05201200"/>
<SAINT SId="13101" CId="13101"/>
<SAINT SId="052002" CId="052002"/>
<SAINT SId="1111" CId="1111"/>
<SAINT SId="263001" CId="263001"/>
<SAINT SId="05200795" CId="05200795"/>
<SAINT SId="05200295" CId="05200295"/>
<SAINT SId="05200895" CId="05200895"/>
<SAINT SId="0520995" CId="0520995"/>
</DAY>
