<DAY>

<SAINT Name="殉道女瓦西利薩（尼科美底亞，309年）" Id="" Type="0" />
<SAINT Name="聖德奧克提斯特（大聖艾弗提彌之同修，451年）" Id="260" Type="1" />
<SAINT Name="殉道司教安提默（尼科美底亞主教）、偕同其就義者：德奧斐洛輔祭、多若德奧、瑪爾多尼、彌格多尼、裴特若、印迪、格爾格尼、茲諾、艾弗提彌、童貞女多穆納（302年）" Id="1439" Type="1" />
<SAINT Name="聖瑞瑪克洛（荷蘭的馬斯特里希特城主教，677年）" Id="" Type="0" />
<SAINT Name="聖女斐維（科林托附近肯赫瑞埃地方之女輔祭，一世紀）" Id="" Type="0" />
<SAINT Name="殉道司教阿里斯提雍（敘利亞的亞歷山大里亞主教，三世紀）" Id="" Type="0" />
<SAINT Name="聖埃谷爾弗（高盧的普羅旺斯，676年）" Id="" Type="0" />
<SAINT Name="聖約安尼基二世（塞爾維亞牧首，1349年）" Id="" Type="0" />
<SAINT Name="蒙福者約安「毛人」（羅斯托夫之聖愚，1580年）" Id="" Type="0" />
<SAINT Name="新殉道者頗利多若（塞浦路斯，1794年）" Id="" Type="0" />
<SAINT Name="聖君士坦丁皇帝（幼者）" Id="" Type="0" />
<SAINT Name="敬遷般塔頗利城主教聖奈克塔里之聖髑紀念日" Id="" Type="0" />
<SAINT Name="聖愛德瓦爾德（即聖愛德華，英格蘭國王，殉道者，978年）" Id="" Type="0" />

</DAY>