<DAY>

<SAINT Name="殉道女玛特若纳（德撒洛尼基，4世纪）" Id="716" Type="1" />
<SAINT Name="殉道者埃玛努伊尔及德奥多西（304年）" Id="717" Type="0" />
<SAINT Name="圣约安（具天眼通者，利科颇利城人，埃及之退隐者，394年）" Id="718" Type="0" />
<SAINT Name="圣基里科（色雷斯地方的可敬者）" Id="" Type="0" />
<SAINT Name="先知阿纳尼亚（见史书补遗二，16章）" Id="" Type="0" />
<SAINT Name="圣帕弗罗（科林托主教，925年）" Id="" Type="0" />
<SAINT Name="圣帕弗努提（大圣安托尼之弟子，4世纪）" Id="" Type="0" />
<SAINT Name="圣艾弗冷（罗斯托夫，1454年）" Id="" Type="0" />
<SAINT Name="圣亚历山大（伏尔加河岸沃彻地方修道院院长，16世纪）" Id="" Type="0" />
<SAINT Name="圣安托尼（托博尔斯科都主教，1740年）" Id="" Type="0" />
<SAINT Name="阿托斯圣山“甘饴之吻”圣母像及“弗坐词”圣母像纪念日。" Id="" Type="0" />

</DAY>