<DAY>

<SAINT Name="弗里吉亞的盎默里亞城四十二名殉道者，知其名者有：君士坦丁、埃提、德奧斐洛、德奧多若、麥利塞諾、卡利斯托、瓦索伊斯（約845年）" Id="579" Type="1" />
<SAINT Name="殉道修士科農及其子科農（伊科尼雍地方，270-275年）" Id="582" Type="0" />
<SAINT Name="聖阿爾卡迪及他的弟子聖猶利安及聖福利（塞浦路斯地方修士，361年）" Id="583" Type="0" />
<SAINT Name="敬遷保加利亞的殉道者阿弗拉穆（1229年就義）之聖髑紀念日（1230年）" Id="" Type="0" />
<SAINT Name="聖弗利多林院長，上萊茵河流域的光照者（538年）" Id="" Type="0" />
<SAINT Name="聖約弗（受大聖衣後更名為伊酥斯）（索洛福基地方，1720年）" Id="6649" Type="0" />
<SAINT Name="聖君後艾萊尼尋獲十字聖架及聖釘紀念日（326年）" Id="2494" Type="0" />
<SAINT Name="琴斯托霍瓦聖母像紀念日（一世紀）莫斯科的「蒙福的天堂」聖母像紀念日（十四世紀）" Id="584" Type="0" />

</DAY>