<DAY>
<LANGUAGE>
<SCRIPTURE Type="apostol" Reading="Philip_2:5-11" Pericope="240" Note="for the Theotokos"/>
<SCRIPTURE Type="gospel" Reading="Lk_10:38-42, 11:27-28" Pericope="54" Note="for the Theotokos"/>
</LANGUAGE>
<LANGUAGE Cmd="LS == 0">
<SAINT Name="Martyrs Adrian and Natalia and 23 Martyrs suffering with them in Nicomedia (+ c 305-311)" Id="74" Type="1" />
<SAINT Name="Venerable Adrian, Abbot of Ondrusovsk (+ 1549)" Id="75" Type="0" />
<SAINT Name="Blessed Cyprian of Storozhevsk" Id="" Type="0" />
<SAINT Name="Venerable Adrian, Abbot of Uglich (16th C)" Id="" Type="0" />
<SAINT Name="Meeting of the Vladimir Icon of the Most Holy Mother of God (1395)" Id="2812" Type="4" />
</LANGUAGE>
<LANGUAGE Cmd="LS == 1">
<SAINT Name="Sts Martyrs Adrien, Nathalie son épouse et leurs 23 compagnons" Id="74" Type="1" />
<SAINT Name="St Martyr Adrien le prince" Id="" Type="0" />
<SAINT Name="Sts Martyrs Attique et Sisinios" Id="" Type="0" />
<SAINT Name="St Tithoès" Id="" Type="0" />
<SAINT Name="St Ibistion" Id="" Type="0" />
<SAINT Name="St Joasaph, Prince des Indes et son père le Roi Abenner" Id="" Type="0" />
<SAINT Name="Sts Adrien, Higoumène du Monastère d'Ondroussov et Cyprien de Storojevsk" Id="75" Type="0" />
<SAINT Name="St Adrien d'Ouglitch, disciple de St Païssios d'Ouglitch" Id="" Type="0" />
</LANGUAGE>
<LANGUAGE Cmd="LS == 3">
<SAINT Name="Мчч. Адриана и Наталии и прочих 23, с ними пострадавших (305-311)" Id="74" Type="1"/>
<SAINT Name="Сретение Владимирской иконы Пресвятой Богородицы (1395)" Id="2812" Type="4"/>
<SAINT Name="Блж. Марии Дивеевской (1931)" Id="" Type="0"/>
<SAINT Name="Сщмч. Петра пресвитера (1918)" Id="" Type="0"/>
<SAINT Name="Св. Георгия исп., пресвитера (1928)" Id="" Type="0"/>
<SAINT Name="Сщмч. Виктора пресвитера, мчч. Димитрия, Петра и св. Романа исп., пресвитера (1937)" Id="4895" Type="0"/>
<SAINT Name="Прп. Адриана Ондрусовского (1549)" Id="75" Type="0"/>
<SAINT Name="Псково-Печерской  именуемой &quot;Умиление&quot;, иконы Божией Матери (1524)" Id="2997" Type="0"/>
</LANGUAGE>
</DAY>
