<SAINT>
<!-- THIS IS THE 24th SATURDAY AFTER PENTECOST -->
<SERVICE Type="0">
<PRIMES Type="Normal"/>
<LITURGY>
<SCRIPTURE Type="apostol" Reading="II Cor_11:1-6" Pericope="191" />
<SCRIPTURE Type="gospel" Reading="Lk_9:37-43a" Pericope="46" EffWeek="25" Cmd="GS == 1 &amp;&amp; ((doy &gt;= 312 &amp;&amp; doy &lt;= 318))"/>
<SCRIPTURE Type="gospel" Reading="Lk_8:16-21" Pericope="36" EffWeek="23" Cmd="GS == 1 &amp;&amp; ((doy &gt;= 298 &amp;&amp; doy &lt;= 304))"/>
<SCRIPTURE Type="gospel" Reading="Lk_9:1-6" Pericope="40" EffWeek="24" Cmd="GS == 1 &amp;&amp; ((doy &gt;= 305 &amp;&amp; doy &lt;= 311))"/>
<SCRIPTURE Type="gospel" Reading="Lk_7:1b-10" Pericope="29" EffWeek="22" Cmd="GS == 1 &amp;&amp; ((doy &gt;= 291 &amp;&amp; doy &lt;= 297))"/>
<SCRIPTURE Type="gospel" Reading="Lk_9:57-62" Pericope="49" EffWeek="26" Cmd="GS == 1 &amp;&amp; ((doy &gt;= 319 &amp;&amp; doy &lt;= 325))"/>
<SCRIPTURE Type="gospel" Reading="Lk_10:19-21" Pericope="51 (mid.)" EffWeek="27" Cmd="GS == 1 &amp;&amp; ((doy &gt;= 326 &amp;&amp; doy &lt;= 332))"/>
<SCRIPTURE Type="gospel" Reading="Lk_9:1-6" Pericope="40" Cmd="GS == 0" /> 
</LITURGY>
</SERVICE>
</SAINT>
