<DAY>
<SAINT Name="9" Cmd="dow == 6" />

<SAINT Name="St Hilarion le Grand" Id="4561" Type="2" />
<SAINT Name="St Philothée de l'Athos" Id="" Type="0" />
<SAINT Name="Sts Gaïus, Dasius et Zotique" Id="4567" Type="0" />
<SAINT Name="St Zacharie, moine" Id="" Type="0" />
<SAINT Name="Ste Théodote et St Socrate" Id="" Type="0" />
<SAINT Name="St Eucratos" Id="" Type="0" />
<SAINT Name="St Baruch" Id="" Type="0" />
<SAINT Name="St Azis" Id="" Type="0" />
<SAINT Name="St Jean de Monembasia" Id="" Type="0" />
<SAINT Name="St Jacques du Monastère du Christ Sauveur" Id="" Type="0" />
<SAINT Name="St Plantin et Ste Irène" Id="" Type="0" />
<SAINT Name="St Hilarion des Grottes de Kiev" Id="932" Type="0" />
<SAINT Name="Sts Théophile et Jacques de Omoutsk (Pskov)" Id="4566" Type="0" />
<SAINT Name="St Hilarion du lac Pskov" Id="933" Type="0" />
<SAINT Name="St Hilarion, Evêque de Meglin en Bulgarie" Id="928" Type="2" />
<SAINT Name="Sts Vessarion, sophrone et Opréa de Roumanie" Id="" Type="0" />
<SAINT Name="Sts Moïse Matsinic de Sibiu et Jean de Galesh" Id="" Type="0" />
<SAINT Name="St Vulfolaïc, stylite de CarignanSte Ursule et ses compagnes à Cologne" Id="" Type="0" />
<SAINT Name="St Fintan de Taghmon" Id="" Type="0" />

</DAY>