<DAY>
<SAINT Name="Άγιοι Ευτρόπιος, Κλεόνικος και Βασιλίσκος" Id="2590" Type=""/>
<SAINT Name="Άγιος Θεοδώρητος ο Ιερομάρτυρας, πρεσβύτερος Αντιοχείας" Id="2593" Type=""/>
<SAINT Name="Όσιοι Ζήνων και Ζωίλος" Id="2594" Type=""/>
<SAINT Name="Οσία Πιαμούν η Παρθένος" Id="2596" Type=""/>
<SAINT Name="Οσία Αλεξάνδρα η εξ Αλεξανδρείας" Id="2597" Type=""/>
<SAINT Name="Σύναξη της Υπεραγίας Θεοτόκου του Βολοκολάμσκ εν Ρωσία" Id="2598" Type=""/>
<SAINT Name="Άγιος Ιωάννης Πατριάρχης Γεωργίας" Id="2600" Type=""/>
<SAINT Name="Άγιοι Εννέα Μάρτυρες οι εκ Γεωργίας" Id="2599" Type=""/>
</DAY>
