<DAY>
<SAINT Name="16" Cmd="dow == 0" />
<SCRIPTURE Type="apostol" Reading="Heb_11:33-40" Pericope="330" Note="for the Youths"/>
<SCRIPTURE Type="gospel" Reading="Lk_11:47-12:1" Pericope="62" Note="for the Youths"/>

<SAINT Name="圣先知达尼伊尔（主降生前600年）及三圣童：阿纳尼雅、阿匝里雅、弥萨伊尔" Id="" Type="0" />
<SAINT Name="三位殉道士兵：帕特尔穆提、科普里、亚历山大（埃及，361年）" Id="" Type="0" />
<SAINT Name="圣斯图尔穆（德意志的弗尔达修道院之建立者和院长，779年）" Id="" Type="0" />
<SAINT Name="圣达尼伊尔（宣信者，受大圣衣后名为斯特梵，西班牙及埃及之修士，10世纪）" Id="" Type="0" />
<SAINT Name="圣阿塔纳西、圣尼科拉、圣安托尼（阿托斯圣山瓦托佩迪修道院之建立者，10世纪）" Id="" Type="0" />
<SAINT Name="新殉道者尼基塔（尼撒地方，1300年）" Id="" Type="0" />
<SAINT Name="圣迪奥尼西（匝金托岛人氏，埃吉纳岛总主教，1622年）" Id="" Type="0" />
<SAINT Name="圣弥撒伊尔（阿巴拉茨克地方之修士司祭，1797年）" Id="" Type="0" />
<SAINT Name="新殉道修士帕伊西（图尔诺沃修道院院长）、殉道辅祭阿瓦库穆（贝尔格莱德，1814年）" Id="" Type="0" />

</DAY>