<DAY>
<SCRIPTURE Type="apostol" Reading="Gal_5:22-6:2" Pericope="213" Note="for St Job"/>
<SCRIPTURE Type="gospel" Reading="Lk_6:17-23" Pericope="24" Note="for St Job"/>

<SAINT Name="Venerable Moses the Black of Scete (+ c 400)" Id="1569" Type="1" />
<SAINT Name="Finding of the relics of the Venerable Job, Abbot and Wonderworker of Pochaev (1659)" Id="91037" Type="4" />
<SAINT Name="Venerable Savva of Pskov (+ 1495)" Id="1895" Type="0" />
<SAINT Name="Righteous Anna the Prophetess, daughter of Phanuel, at the Temple in Jerusalem (1st C)" Id="2396" Type="0" />
<SAINT Name="Righteous Hezekiah, King of Judea (721-691 BC)" Id="" Type="0" />
<SAINT Name="Synaxis of all the saints who have shown forth in the Kiev Far Caves" Id="" Type="0" />
<SAINT Name="St Amphilochius, Bishop of Vladimir Volynskiy" Id="" Type="0" />
<SAINT Name="Martyr Susanna, Princess of Rana, Georgia (5th C)" Id="4539" Type="0" />
<SAINT Name="New Hieromartyr Archimandrite Sergius and 11 monks of Zilantiev Monastery (+1918)" Id="4892" Type="0" />

</DAY>
