<?xml version="1.0" encoding="UTF-8" standalone="no"?><SAINT>
<NAME Genetive="Навечерия Богоявления" Nominative="Навечерие Богоявления" Short="Навечерие"/> 
<SERVICE>
<LITURGY>
<TROPARION Tone="4" Type="1">
Возвраща́шесѧ и҆ногда̀ і҆ѻрда́нъ рѣка̀ ми́лѡтїю є҆лїссе́овою, возне́сшꙋсѧ и҆лїѝ, и҆ раздѣлѧ́хꙋсѧ во́ды сю́дꙋ и҆ сю́дꙋ, и҆ бы́сть є҆мꙋ̀ сꙋ́хъ пꙋ́ть, и҆́же мо́крый, во ѡ҆́бразъ вои́стиннꙋ кр҃ще́нїѧ, и҆́мже мы̀ текꙋ́щее житїѧ̀ прехо́димъ ше́ствїе: хрⷭ҇то́съ ꙗ҆ви́сѧ во і҆ѻрда́нѣ ѡ҆ст҃и́ти во́ды. 
</TROPARION>
<KONTAKION Podoben="3" Tone="4" Type="1">Во стрꙋѧ́хъ дне́сь і҆ѻрда́нскихъ бы́въ гдⷭ҇ь, і҆ѡа́ннꙋ вопїе́тъ: не ᲂу҆бо́йсѧ крести́ти мѧ̀, спасти́ бо прїидо́хъ а҆да́ма первозда́ннаго.</KONTAKION>
</LITURGY>
</SERVICE>
</SAINT>