<?xml version="1.0" encoding="UTF-8" standalone="no"?><SAINT>
<NAME Nominative="Прпⷣбнагѡ ѳеофа́на и҆сповѣ́дника, творца̀ канѡ́нѡвъ, є҆пі́скопа нїкі́йскагѡ (ок. 850)"/>
<NAME Short="Прпⷣбнагѡ ѳеофа́на"/>
<SERVICE Type="1"/>
<SERVICE><LITURGY><TROPARION Tone="0" Type="1">Правосла́вїѧ наста́вниче, благоче́стїѧ ᲂу҆чи́телю и҆ чистоты̀, вселе́нныѧ свѣти́льниче, а҆рхїере́ѡвъ бг҃одꙋхнове́нное ᲂу҆добре́нїе, ѳеофа́не премꙋ́дре, ᲂу҆че́ньми твои́ми всѧ̑ просвѣти́лъ є҆сѝ: цѣвни́це дꙋхо́внаѧ, молѝ хрⷭ҇та̀ бг҃а, спасти́сѧ дꙋша́мъ на́шымъ.</TROPARION><KONTAKION Podoben="3" Tone="2" Type="1">Возгремѣ́въ хрⷭ҇то́во бжⷭ҇твенное воплоще́нїе, безплѡ́тныѧ врагѝ до конца̀ ѡ҆бличи́лъ є҆сѝ, чꙋ́дне ѳеофа́не. сегѡ̀ ра́ди всѝ вѣ́рнѡ и҆ благоче́стнѡ вопїе́мъ тѝ: молѝ непреста́ннѡ ѡ҆ всѣ́хъ на́съ. </KONTAKION></LITURGY></SERVICE></SAINT>