<?xml version="1.0" encoding="UTF-8" standalone="no"?><SAINT>
<NAME Nominative="Недѣ́лѧ блꙋ́днагѡ сы́на" Short="Недѣ́лѧ"/>
<SERVICE><LITURGY><TROPARION Tone="" Type="1"/><KONTAKION Podoben="1" Tone="3" Type="1">Ѻ҆ч҃ескїѧ сла́вы твоеѧ̀ ᲂу҆дали́хсѧ безꙋ́мнѡ, въ ѕлы́хъ расточи́въ є҆́же мѝ пре́далъ є҆сѝ бога́тство. тѣ́мже тѝ блꙋ́днагѡ гла́съ приношꙋ̀: согрѣши́хъ пред̾ тобо́ю ѻ҆́ч҃е ще́дрый, прїими́ мѧ ка́ющасѧ, и҆ сотвори́ мѧ ꙗ҆́кѡ є҆ди́наго ѿ нає́мникъ твои́хъ.</KONTAKION></LITURGY></SERVICE></SAINT>