<DAY>

<SAINT Name="Sts Martyrs Thallelaios, Alexandre et Astérios" Id="1108" Type="1" />
<SAINT Name="Ste Lydie" Id="" Type="0" />
<SAINT Name="St Ascla" Id="1109" Type="0" />
<SAINT Name="Sts Nicétas, Jean et Joseph, fondateurs du Monastère Néa-Moni à Chio" Id="" Type="0" />
<SAINT Name="St Thalassios le Lybien" Id="" Type="0" />
<SAINT Name="St Marc l'Ermite" Id="" Type="0" />
<SAINT Name="St Dovmont-Timothée, Prince de Pskov" Id="1111" Type="0" />
<SAINT Name="St Etienne de Piperi en Serbie" Id="" Type="0" />
<SAINT Name="St Alexis, Métropolite de Kiev (invention des Reliques)" Id="131" Type="3" />
<SAINT Name="St Dido, disciple de St David de Géorgie" Id="" Type="0" />
<SAINT Name="St Baudile, Evêque de Nîmes" Id="" Type="0" />

</DAY>