<SAINT>
<NAME Nominative="Όσιοι Ζεβινάς, Πολυχρόνιος, Δαμιανός και Μωυσής"/>
<LIFE Id="saintgr" Copyright="saint.gr">
Ο Όσιος Ζεβινάς έστησε το ασκητήριό του σε όρος και εκεί ασκήτεψε με προσευχή και νηστεία. Κοντά του προσήλθε και ο Όσιος Πολυχρόνιος, ο οποίος μιμήθηκε τον Όσιο διδάσκαλό του στην αδιάλειπτη προσευχή και εγκράτεια.<br /><br />Οι Όσιοι Δαμιανός και Μωυσής υπήρξαν μαθητές του Οσίου Πολυχρονίου. Στο Συναξάρι αναφέρεται, ότι ο Όσιος Μωυσής κατοίκησε στο κελί του Γέροντός του, ενώ ο Όσιος Δαμιανός πήγε στην κωμόπολη Νιαρά, όπου κοντά στα αλώνια βρήκε έναν έρημο οικίσκο και έζησε σαν ερημίτης.<br /><br />Οι Όσιοι και Θεοφόροι Πατέρες μας, κοιμήθηκαν με ειρήνη.<br /><br />Τους βίους των Οσίων, συνέγραψε ο Κύρου Θεοδώρητος στη Φιλόθεο Ιστορία του.
</LIFE>
</SAINT>
