<DAY>
<SAINT Name="Άγιοι Φιλήμων ο Απόστολος, Άρχιππος, Ονήσιμος και Απφία" Id="4601" Type=""/>
<SAINT Name="Άγιοι Κικιλία, Βαλεριανός και Τιβούρτιος" Id="4605" Type=""/>
<SAINT Name="Όσιος Αββάς" Id="4614" Type=""/>
<SAINT Name="Άγιος Μάξιμος ο Καπιτουλάριος" Id="4608" Type=""/>
<SAINT Name="Άγιοι Μάρκος, Στέφανος και Μάρκος" Id="4609" Type=""/>
<SAINT Name="Άγιος Προκόπιος ο Παλαιστίνιος" Id="4612" Type=""/>
<SAINT Name="Άγιος Μένιγνος ο κναφέας" Id="4613" Type=""/>
<SAINT Name="Όσιος Κάλλιστος ο Β', Πατριάρχης Κωνσταντινούπολης" Id="4615" Type=""/>
<SAINT Name="Άγιοι Χριστόφορος και Ευφημία" Id="4616" Type=""/>
<SAINT Name="Άγιοι Θαλαλαίος και Άνθιμος" Id="4618" Type=""/>
<SAINT Name="Άγιος Θαδδαίος" Id="4620" Type=""/>
<SAINT Name="Άγιος Αγαπίων ο Ρωμαίος" Id="4621" Type=""/>
<SAINT Name="Άγιος Αγάπιος" Id="4622" Type=""/>
<SAINT Name="Άγιος Σισίνιος ο Ιερομάρτυρας" Id="4623" Type=""/>
<SAINT Name="Άγιος Κλήμης ο Θαυματουργός επίσκοπος Αχρίδας της Βουλγαρίας" Id="4624" Type=""/>
<SAINT Name="Όσιος Γερμανός Ιδρυτής Ιεράς Μονής Εικοσιφοινίσσης" Id="4625" Type=""/>
</DAY>
