<DAY>

<SAINT Name="圣达玛里斯（雅典，1世纪）" Id="" Type="0" />
<SAINT Name="殉道司祭基普里安及童贞殉道女犹斯提纳（尼科美底亚，304年）" Id="" Type="0" />
<SAINT Name="圣勒格尔（奥吞主教，677年）" Id="" Type="0" />
<SAINT Name="殉道者：达维德、君士坦丁（格鲁吉亚的阿尔格维体王子，740年）" Id="" Type="0" />
<SAINT Name="蒙福者安德列（君士坦丁堡之圣愚，911年）" Id="" Type="0" />
<SAINT Name="大殉道者德奥多若（庞都的哈尔迪亚的阿特兰地方，1180年）" Id="" Type="0" />
<SAINT Name="圣女安纳（喀施因地方，1338年）" Id="" Type="0" />
<SAINT Name="圣卡西安（乌格利奇修士，1504年）" Id="" Type="0" />
<SAINT Name="蒙福者基普里安（苏兹达尔之圣愚，1622年）" Id="" Type="0" />
<SAINT Name="新殉道者格奥尔吉（小亚西亚的费拉德尔菲亚，1794年）" Id="" Type="0" />
<SAINT Name="圣德奥多若（俄国海军上将，1817年）" Id="" Type="0" />

</DAY>