<DAY>
<SAINT Name="4" Cmd="dow == 0" />
<SAINT Name="11" Cmd="dow == 6" />

<SAINT Name="舉揚聖架節慶期" Id="" Type="0" />
<SAINT Name="殉道司教：伊拉克利迪、彌榮（均為塞浦路斯主教，一世紀）" Id="" Type="0" />
<SAINT Name="殉道婦索斐亞及其三女：信（彼斯提斯／維拉）、望（埃爾彼斯／納德志達）、愛（阿伽彼／琉博弗）（羅馬城，137年）" Id="2434" Type="1"  />
<SAINT Name="巴勒斯坦之一百五十六名殉道者，包括：主教佩萊、主教尼爾、司祭茲諾、貴族帕提爾穆提、貴族伊利亞（310年）" Id="" Type="0" />
<SAINT Name="殉道女德奧多塔（尼西亞，230年）" Id="" Type="0" />
<SAINT Name="殉道婦路基亞及其子革彌尼安（羅馬，303年）" Id="" Type="0" />
<SAINT Name="殉道司祭朗博特（荷蘭的馬斯特里希特城市，704年）" Id="" Type="0" />
<SAINT Name="紀念埃及之一百位殉道者" Id="" Type="0" />
<SAINT Name="聖阿納斯塔西（塞浦路斯的佩里奧特榮地方，十二世紀）" Id="" Type="0" />
<SAINT Name="聖艾弗西彼（塞浦路斯）" Id="" Type="0" />

</DAY>