<DAY>
<SAINT Name="2" Cmd="dow == 0" />
<SAINT Name="8" Cmd="dow == 6" />
<SCRIPTURE Type="matins" Reading="Jn_10:1-9" Pericope="35 (mid)" Cmd="dow != 0"/>
<SCRIPTURE Type="apostol" Reading="Heb_7:26-8:2" Pericope="318" Note="for St Peter"/>
<SCRIPTURE Type="gospel" Reading="Lk_6:17-23" Pericope="24" Note="for St Peter"/>

<SAINT Name="Ste Julienne de Nicomédie" Id="3159" Type="1" />
<SAINT Name="St Thémistocle de Myre" Id="3163" Type="0" />
<SAINT Name="St Pierre, Métropolite de Moscou" Id="1779" Type="4" />
<SAINT Name="Ste Julienne, Princesse de Vyazmsk" Id="2526" Type="0" />
<SAINT Name="St Procope de Vyatsk" Id="3162" Type="0" />

</DAY>
