<DAY>
<LANGUAGE Cmd="LS == 0">
<SAINT Name="Venerable Athanasius, Founder of the Great Lavra on Mt Athos, and his 6 disciples (+ 1000)" Id="293" Type="4" />
<SAINT Name="Uncovering of the relics of the Venerable Sergius of Radonezh (1422)" Id="1974" Type="3" />
<SAINT Name="Martyrs Anna of Rome and Cyrilla, of Cyrene in Libya (+304)" Id="2372" Type="0" />
<SAINT Name="Venerable Lampados the Wonderworker" Id="" Type="0" />
<SAINT Name="Venerable Cyprian of Mt. Athos" Id="" Type="0" />
<SAINT Name="Venerable Athanasius the Hermit" Id="" Type="0" />
<SAINT Name="Venerable Martyrs Grand Duchess Elizabeth, Nun Barbara, and with them the Princes: John, Igor, Constantine, Sergius, and Vladimir, at Alapayevsk (+ 1918)" Id="2500" Type="3" />
</LANGUAGE>
<LANGUAGE Cmd="LS == 1">
<SAINT Name="St Athanase l'Athonite, fondateur de la Grande Lavra" Id="293" Type="4" />
<SAINT Name="St Lampade le Thaumaturge" Id="" Type="0" />
<SAINT Name="Sts Basile et ses 70 compagnons à Scythopolis" Id="" Type="0" />
<SAINT Name="Ste Cyrilla de Cyrène" Id="" Type="0" />
<SAINT Name="St Cyprien le Jeune" Id="" Type="0" />
<SAINT Name="Synaxe des Sts de Lesbos" Id="" Type="0" />
<SAINT Name="Sts Athanase et Théodose de Cherepovetsk (Novgorod)" Id="" Type="0" />
<SAINT Name="St Serge de Radonège (Invention des Reliques)" Id="1974" Type="3" />
<SAINT Name="St Valier, Evêque de Couserans" Id="" Type="0" />
<SAINT Name="Ste Martyre Princesse Elizabeth et moine Barbare, et Princes Martyres Jean, Igor, Constantine, Serge et Vladimir, tues a Alapaievsk" Id="2500" Type="3"/>
</LANGUAGE>
<LANGUAGE Cmd="LS == 3">
<SAINT Name="Прп. Афанасия Афонского (1000)" Id="293" Type="4"/>
<SAINT Name="Обретение честных мощей прп. Сергия, игумена Радонежского (1422)" Id="1974" Type="3"/>
<SAINT Name="Прмцц. вел. кн. Елисаветы и инокини Варвары, князей Иоанна, Игоря, Константина, Сергия и Владимира, в Алапаевске убиенных  (1918)" Id="2500" Type="3"/>
<SAINT Name="Прп. Агапита исп (1936)" Id="" Type="0"/>
<SAINT Name="Мцц. Анны и Кириллы (304)" Id="2372" Type="0"/>
<SAINT Name="Прп. Лампада Иринопольского (X)" Id="" Type="0"/>
<SAINT Name="Иконы Божией Матери, именуемой &quot;Экономисса&quot;" Id="" Type="0"/>
</LANGUAGE>
<LANGUAGE Cmd="LS == 5">
<SAINT Name="圣阿塔纳西（阿托斯圣山之大成德者，1003年）及其6名圣弟子" Id="293" Type="4" />
<SAINT Name="寻获拉多奈哲的圣塞尔吉（1392年）之圣髑纪念日（1422年）" Id="" Type="0" />
<SAINT Name="殉道司教圣斯特梵（使徒帕弗罗之弟子，瑞吉翁地方之主教）、偕同其就义者：主教苏埃若；殉道女：阿格尼斯、斐利基塔、佩尔佩图亚（一世纪）" Id="" Type="0" />
<SAINT Name="殉道者安纳（罗马，304年）" Id="" Type="0" />
<SAINT Name="殉道者阿塔纳西（耶路撒冷之辅祭，451年）" Id="" Type="0" />
<SAINT Name="圣郎帕多（伊里诺颇利之修士，10世纪）" Id="" Type="0" />
<SAINT Name="圣阿塔纳西及圣德奥多西（均为拉多奈哲的圣塞尔吉的弟子，切瑞颇维茨地方，1382年）" Id="" Type="0" />
<SAINT Name="新殉道者基普里安（阿托斯圣山，库特路穆西邬修道院，1679年）" Id="" Type="0" />
<SAINT Name="殉道女：埃利撒维特•罗曼诺夫及修女瓦尔瓦拉（俄罗斯，1918年）" Id="" Type="0" />
<SAINT Name="纪念莱斯博斯岛之23位圣徒" Id="" Type="0" />
<SAINT Name="圣女摩尔文纳（英格兰的摩尔文斯托之女施主，6世纪）" Id="" Type="0" />
</LANGUAGE>
<LANGUAGE Cmd="LS == 6">
<SAINT Name="聖阿塔納西（阿托斯聖山之大成德者，1003年）及其六名聖弟子" Id="" Type="0" />
<SAINT Name="尋獲拉多奈哲的聖塞爾吉（1392年）之聖髑紀念日（1422年）" Id="" Type="0" />
<SAINT Name="殉道司教聖斯特梵（使徒帕弗羅之弟子，瑞吉翁地方之主教）、偕同其就義者：主教蘇埃若；殉道女：阿格尼斯、斐利基塔、佩爾佩圖亞（一世紀）" Id="" Type="0" />
<SAINT Name="殉道者安納（羅馬，304年）" Id="" Type="0" />
<SAINT Name="殉道者阿塔納西（耶路撒冷之輔祭，451年）" Id="" Type="0" />
<SAINT Name="聖郎帕多（伊里諾頗利之修士，十世紀）" Id="" Type="0" />
<SAINT Name="聖阿塔納西及聖德奧多西（均為拉多奈哲的聖塞爾吉的弟子，切瑞頗維茨地方，1382年）" Id="" Type="0" />
<SAINT Name="新殉道者基普里安（阿托斯聖山，庫特路穆西鄔修道院，1679年）" Id="" Type="0" />
<SAINT Name="殉道女：埃利撒維特•羅曼諾夫及修女瓦爾瓦拉（俄羅斯，1918年）" Id="" Type="0" />
<SAINT Name="紀念萊斯博斯島之二十三位聖徒" Id="" Type="0" />
<SAINT Name="聖女摩爾文納（英格蘭的摩爾文斯托之女施主，六世紀）" Id="" Type="0" />
</LANGUAGE>
</DAY>
