<DAY>
<SCRIPTURE Type="vespers" Reading="I Jn_3:21-4:6" Note="for the Apostle"/>
<SCRIPTURE Type="vespers" Reading="I Jn_4:11-16" Note="for the Apostle"/>
<SCRIPTURE Type="vespers" Reading="I Jn_4:20-5:5" Note="for the Apostle"/>
<SCRIPTURE Type="matins" Reading="Jn_21:15-25" Pericope="67" Cmd="dow != 0" Note="for the Apostle"/>
<SCRIPTURE Type="apostol" Reading="I Jn_1:1-7" Pericope="68" Note="for the Apostle"/>
<SCRIPTURE Type="gospel" Reading="Jn_19:25-27, 21:24-25" Pericope="61" Note="for the Apostle"/>

<SAINT Name="聖使徒，著福音者，神學家約安（98-117年間）" Id="962" Type="5" />
<SAINT Name="大聖阿爾塞尼（斯基提斯地方，448年）" Id="9262" Type="1" />
<SAINT Name="新殉道者尼基佛若（1942年）" Id="" Type="0"/>
<SAINT Name="聖阿爾塞尼（被稱為「勤勞者」基輔洞窟修道院修士，十四世紀）及聖彼敏（十二世紀）" Id="4390" Type="0" />
<SAINT Name="聖婦艾彌利亞（大聖瓦西里，尼撒主教聖格里高利及聖女瑪克里納之生母，375年）" Id="" Type="0" />
<SAINT Name="聖女伊杜貝爾伽（荷蘭的尼吉維爾城的建立者，652年）" Id="" Type="0" />
<SAINT Name="聖耶拉克斯（埃及，五世紀）" Id="" Type="0" />
<SAINT Name="聖瑪喀里（格恆特總主教，1012年）" Id="" Type="0" />
<SAINT Name="敬遷諾夫哥羅德的聖愚阿爾塞尼（1570年）之聖髑紀念日（1785年）" Id="" Type="0" />
<SAINT Name="卡西奧彼亞聖母像治癒瞽目者斯特梵之奇蹟紀念日" Id="" Type="0" />

</DAY>